[{"time": {"modified": "Mon Nov 11 12:31:18 2019", "created": "Wed Jul 31 12:16:31 2019"}, "file": "C:\\xampp\\htdocs\\Gotyou\\11.txt"}, {"time": {"modified": "Fri Nov  8 16:51:01 2019", "created": "Fri Nov  8 15:56:00 2019"}, "file": "C:\\xampp\\htdocs\\Gotyou\\Crazy.py"}, {"time": {"modified": "Tue Jul 30 14:04:18 2019", "created": "Tue Jul 30 13:49:25 2019"}, "file": "C:\\xampp\\htdocs\\Gotyou\\democut.php"}, {"time": {"modified": "Thu Aug  1 17:59:13 2019", "created": "Thu Aug  1 17:30:17 2019"}, "file": "C:\\xampp\\htdocs\\Gotyou\\FairTeamAlog.php"}, {"time": {"modified": "Fri Oct 25 11:35:15 2019", "created": "Thu Oct 24 15:56:10 2019"}, "file": "C:\\xampp\\htdocs\\Gotyou\\forkphp.php"}, {"time": {"modified": "Thu Aug  1 16:55:40 2019", "created": "Thu Aug  1 16:24:45 2019"}, "file": "C:\\xampp\\htdocs\\Gotyou\\Id.txt"}, {"time": {"modified": "Thu Aug 30 11:06:22 2018", "created": "Mon Nov  4 14:15:44 2019"}, "file": "C:\\xampp\\htdocs\\Gotyou\\imagecreator.php"}, {"time": {"modified": "Tue Oct  1 11:26:08 2019", "created": "Tue Sep 17 12:54:01 2019"}, "file": "C:\\xampp\\htdocs\\Gotyou\\Jbong.py"}, {"time": {"modified": "Mon May 27 14:41:27 2019", "created": "Mon May 27 14:41:27 2019"}, "file": "C:\\xampp\\htdocs\\Gotyou\\manifest.json"}, {"time": {"modified": "Tue Oct  1 11:30:36 2019", "created": "Tue Oct  1 11:22:35 2019"}, "file": "C:\\xampp\\htdocs\\Gotyou\\Myntrapull.php"}, {"time": {"modified": "Thu Aug  1 15:47:42 2019", "created": "Thu Aug  1 15:47:42 2019"}, "file": "C:\\xampp\\htdocs\\Gotyou\\player.json"}, {"time": {"modified": "Thu Aug  1 15:59:41 2019", "created": "Wed Jul 31 11:26:12 2019"}, "file": "C:\\xampp\\htdocs\\Gotyou\\ranker.php"}, {"time": {"modified": "Thu Aug  1 16:55:04 2019", "created": "Mon May 27 12:57:35 2019"}, "file": "C:\\xampp\\htdocs\\Gotyou\\scaraper.py"}, {"time": {"modified": "Thu Aug  1 15:47:25 2019", "created": "Tue Jul 30 11:07:24 2019"}, "file": "C:\\xampp\\htdocs\\Gotyou\\teamer.php"}, {"time": {"modified": "Thu Aug  1 17:31:17 2019", "created": "Thu Aug  1 16:55:44 2019"}, "file": "C:\\xampp\\htdocs\\Gotyou\\values.txt"}, {"time": {"modified": "Mon Nov 11 12:38:12 2019", "created": "Fri Nov  8 17:02:45 2019"}, "file": "C:\\xampp\\htdocs\\Gotyou\\Filepusher\\filelist.json"}, {"time": {"modified": "Mon Nov 11 12:54:48 2019", "created": "Fri Nov  8 14:40:00 2019"}, "file": "C:\\xampp\\htdocs\\Gotyou\\Filepusher\\filepusher.py"}]